{"resource": {
	"language":"rus",
	"title":[
		{
		"value":"Productivity of Lonicera caeruleae L.",
	"language":"eng"
	},
	{
		"value":"Продуктивность жимолости синей (Lonicera caeruleae L.)",
	"language":"rus"
	}
	],
	"subject":[
		{
		"value":"yields",
	"language":"eng"
	},
	{
		"value":"productividad",
	"language":"esp"
	},
	{
		"value":"rendimiento",
	"language":"esp"
	},
	{
		"value":"provenance",
	"language":"fre"
	},
	{
		"value":"rendement",
	"language":"fre"
	},
	{
		"value":"procedencia",
	"language":"esp"
	},
	{
		"value":"varia©ta©",
	"language":"fre"
	},
	{
		"value":"productivita©",
	"language":"fre"
	},
	{
		"value":"belarus",
	"language":"esp"
	},
	{
		"value":"varieties",
	"language":"eng"
	},
	{
		"value":"lonicera",
	"language":"esp"
	},
	{
		"value":"productivity",
	"language":"eng"
	},
	{
		"value":"ba©larus",
	"language":"fre"
	},
	{
		"value":"variedades",
	"language":"esp"
	}
	],
	"page_start":47,
	"page_end":50,
	"uri":"http://agris.fao.org/aos/records/BY2016000471",
	"arn":"BY2016000471",
	"type":"Summary",
	"source":
		{"uri":"http://ring.ciard.net/node/10606"
	},
	"is_part_of":[
		{
		"uri":"http://aims.fao.org/serials/c_e407451c"
	},
	{
		"journal":
		{"title":"Bulletin of the Belarussian State Agricultural Academy : the guidance journal",
	"issn":"2076-5215"
	}
	}
	],
	"date_issued":2013,
	"url":"http://elc.baa.by/vestnik2013-2/vestnik_2_2013.rar",
	"date_submitted":2016,
	"author":[
		{
		"person":
		{"name":"Pigul, M.L."
	}
	},
	{
		"person":
		{"name":"Shalkevich, M.S., National Academy of Sciences. Scientific and Practical Center for Potato, Vegetable and Fruit Growing (Belarus). Institute for Fruit Growing"
	}
	}
	],
	"issue":2,
	"abstract":
		{"value":"The article presents results of research in the conditions of Belarus into 14 variety samples of Lonicera caeruleae L. of different geographic and genetic origin according to their productivity. The best combination of productivity components (total length of growth increase, the number of double-flowers per one running metre, average weight of fruit) was in the variety Sirius, which determined its maximal potential productivity – 7.2 t/ha. Varieties Ognenny opal, Selena, Volkhova and hybrid № 3 had not much lower potential productivity. The degree of realization of productivity potential varied from 48 to 85 %, and this indicator was maximal in the variety Lux. High degree of potential productivity was in the varieties Volkhova, Ognenny opal, Slavyanka, Sodruzhestvo, Solovey, Suvenir and hybrid № 2.",
	"language":"eng"
	}
	}}
