{"resource": {
	"language":"rus",
	"title":[
		{
		"value":"Повышение эффективности производства молока на основе совершенствования структуры рационов кормления коров",
	"language":"rus"
	},
	{"value":"Increase of milk production efficiency upon development of cattle feeding rations' structure"},
	{"value":"Increase of milk production efficiency upon development of cattle feeding rations' structure"}
	],
	"subject":[
		{
		"value":"industrie laitiaёre",
	"language":"fre"
	},
	{
		"value":"industria lechera",
	"language":"esp"
	},
	{
		"value":"rations",
	"language":"eng"
	},
	{
		"value":"livestock management",
	"language":"eng"
	},
	{
		"value":"production laitiaёre",
	"language":"fre"
	},
	{
		"value":"raciones",
	"language":"esp"
	},
	{
		"value":"eficacia",
	"language":"esp"
	},
	{
		"value":"profitability",
	"language":"eng"
	},
	{
		"value":"feeding",
	"language":"eng"
	},
	{
		"value":"rentabilita©",
	"language":"fre"
	},
	{
		"value":"producciaіn lechera",
	"language":"esp"
	},
	{
		"value":"alimentaciaіn",
	"language":"esp"
	},
	{
		"value":"feeding systems",
	"language":"eng"
	},
	{
		"value":"alimentation",
	"language":"fre"
	},
	{
		"value":"efficacita©",
	"language":"fre"
	},
	{
		"value":"valeur a©conomique",
	"language":"fre"
	},
	{
		"value":"dairying",
	"language":"eng"
	},
	{
		"value":"rentabilidad",
	"language":"esp"
	},
	{
		"value":"sistemas de alimentaciaіn",
	"language":"esp"
	},
	{
		"value":"dairy industry",
	"language":"eng"
	},
	{
		"value":"technique d'alimentation",
	"language":"fre"
	},
	{
		"value":"ration",
	"language":"fre"
	},
	{
		"value":"efficiency",
	"language":"eng"
	},
	{
		"value":"manejo del ganado",
	"language":"esp"
	},
	{
		"value":"economic value",
	"language":"eng"
	},
	{
		"value":"valor econaіmico",
	"language":"esp"
	},
	{
		"value":"belarus",
	"language":"esp"
	},
	{
		"value":"improvement",
	"language":"eng"
	},
	{
		"value":"ba©larus",
	"language":"fre"
	},
	{
		"value":"conduite d'a©levage",
	"language":"fre"
	},
	{
		"value":"milk production",
	"language":"eng"
	}
	],
	"page_start":16,
	"page_end":18,
	"uri":"http://agris.fao.org/aos/records/BY2016000558",
	"arn":"BY2016000558",
	"type":"Summary",
	"source":
		{"uri":"http://ring.ciard.net/node/10606"
	},
	"is_part_of":[
		{
		"uri":"http://aims.fao.org/serials/c_4cbf4c2d"
	},
	{
		"journal":
		{"title":"Agropanorama : scientific and technical journal for the agro-industrial complex workers",
	"issn":"2078-7138"
	}
	}
	],
	"date_issued":2013,
	"url":"http://www.batu.edu.by/sites/default/files/u8/AgroP-2013-4-int.pdf",
	"date_submitted":2016,
	"author":
		{"person":
		{"name":"Radko, M.M., Belarus State Agrarian Technical Univ., Minsk (Belarus)"
	}
	},
	"issue":4,
	"abstract":
		{"value":"Dairy industry appears one of the most important economic sectors of the Republic of Belarus, occupying more than 45% of total salable livestock products and about 30% of gross agricultural product. The priority directions of the development of the state, determined by Governmental program, suppose further intensification of the dairy industry with increase of annual milk production up to 10 million tons.  Development of the milk-producing branch directly depends on realization of the complex of measures, influencing the competitiveness of the milk production due to decline of production expenses. The article analyzes the problem of the improvement of the quality of balanced feeds and application of innovative (resource saving) technologies in dairy cattle breeding that brings about the increase of productivity of the branch and reduces the running costs of the economic sector. Upon the example of a dairy enterprise 'Klenovichy' evaluation of the use of additional feeds in dairy cattle's rations is made; financial results of the production and disposal of milk are analyzed.",
	"language":"eng"
	}
	}}
