{"resource": {
	"language":"rus",
	"title":[
		{
		"value":"Content and removal of main feeding elements by different vegetable bean varieties",
	"language":"eng"
	},
	{
		"value":"Содержания и вынос основных элементов питания различными сортами овощной фасоли",
	"language":"rus"
	}
	],
	"subject":[
		{
		"value":"teneur en a©la©ments mina©raux",
	"language":"fre"
	},
	{
		"value":"nutrientes minerales",
	"language":"esp"
	},
	{
		"value":"podzol",
	"language":"fre"
	},
	{
		"value":"la©gumineuse aa grains",
	"language":"fre"
	},
	{
		"value":"substance nutritive",
	"language":"fre"
	},
	{
		"value":"type de sol ga©na©tique",
	"language":"fre"
	},
	{
		"value":"contenido mineral",
	"language":"esp"
	},
	{
		"value":"podzols",
	"language":"eng"
	},
	{
		"value":"stade de da©veloppement va©ga©tal",
	"language":"fre"
	},
	{
		"value":"podzoles",
	"language":"esp"
	},
	{
		"value":"grain legumes",
	"language":"eng"
	},
	{
		"value":"nutrients",
	"language":"eng"
	},
	{
		"value":"plant developmental stages",
	"language":"eng"
	},
	{
		"value":"mineral nutrients",
	"language":"eng"
	},
	{
		"value":"genetic soil types",
	"language":"eng"
	},
	{
		"value":"etapas de desarrollo de la planta",
	"language":"esp"
	},
	{
		"value":"nutrientes",
	"language":"esp"
	},
	{
		"value":"substance nutritive mina©rale",
	"language":"fre"
	},
	{
		"value":"mineral content",
	"language":"eng"
	},
	{
		"value":"belarus",
	"language":"esp"
	},
	{
		"value":"ba©larus",
	"language":"fre"
	},
	{
		"value":"tipos gena©ticos de suelos",
	"language":"esp"
	},
	{
		"value":"beans",
	"language":"eng"
	},
	{
		"value":"leguminosas de grano",
	"language":"esp"
	}
	],
	"page_start":25,
	"page_end":27,
	"uri":"http://agris.fao.org/aos/records/BY2016000176",
	"arn":"BY2016000176",
	"type":"Summary",
	"source":
		{"uri":"http://ring.ciard.net/node/10606"
	},
	"is_part_of":[
		{
		"uri":"http://aims.fao.org/serials/c_870b7376"
	},
	{
		"journal":
		{"title":"Agriculture and Plant Protection : scientific-practical journal",
	"issn":"2220-8003"
	}
	}
	],
	"date_issued":2013,
	"url":"http://izr.by/doc/3_2013.pdf",
	"date_submitted":2016,
	"author":[
		{
		"person":
		{"name":"Skorina, V.V."
	}
	},
	{
		"person":
		{"name":"Pugachev, R.M., Belarus State Academy of Agriculture, Gorki (Belarus)"
	}
	},
	{
		"person":
		{"name":"Bosak, V.N., Belarus State Technological Univ., Minsk (Belarus)"
	}
	}
	],
	"issue":3,
	"abstract":
		{"value":"The purpose of the realized in the conditions of the Republic of Belarus study was to examine the contents of major nutrients in common bean (Phaseolus vulgaris) and the tops of vegetable bean, as well as general and specific removal of nutritive elements by vegetable beans at its cultivation on sod-podzolic medium loamy soil. In studies in cultivated sod-podzolic medium loamy soil were found that total nitrogen content in the beans of different varieties of vegetable beans in a phase of technological maturity, averaged 2.76%, phosphorus – 0.70%, potassium – 2.97%, calcium – 0.59%, magnesium – 0.62% in dry matter. Regulatory takeaway of main nutrients from 1 t of marketable products was 7.6 kg (N), 2.3 (P2O5), 10.1 (K2O), 2.1 (CaO) and 2.1 kg (MgO).",
	"language":"eng"
	}
	}}
