{"resource": {
	"dct:issued":2011,
	"dct:dateSubmitted":2016,
	"dct:language":"por",
	"dct:title":{"value":"Ensino de evolução laico, mas pluricultural",
	"xml:lang":"por"
	},
	"dct:creator":{"foaf:Person":{"foaf:name":"David Figueiredo de Almeida "
	}
	},
	"rdf:about":"http://agris.fao.org/aos/records/BR2015M00067",
	"dct:identifier":"BR2015M00067",
	"dct:type":"Journal Article",
	"dct:source":{"rdf:resource":"http://ring.ciard.net/node/19747"
	},
	"bibo:abstract":{"value":"Neste ensaio, defende-se uma proposta para o ensino da Teoria da Evolução, muitas vezes problemático por se chocar com outras “visões de mundo”. Conceitos como Etnocentrismo, Apartheid Cognitivo e Pluralismo Cultural servem como direcionadores de uma discussão que defende o diálogo entre diferentes “visões de mundo” em prol do Ensino de Evolução.",
	"xml:lang":"por"
	},
	"dct:isPartOf":{"bibo:Journal":{"dct:title":{"value":"Estação Científica (UNIFAP)"}
	}
	}
	}}
